fernetencryption/__init__.py
fernetencryption/__main__.py
fernetencryption/fernetenc.py
fernetencryption/main.py
FernetEncryption-0.1.3.dist-info/LICENSE
FernetEncryption-0.1.3.dist-info/METADATA
FernetEncryption-0.1.3.dist-info/WHEEL
FernetEncryption-0.1.3.dist-info/entry_points.txt
FernetEncryption-0.1.3.dist-info/top_level.txt
FernetEncryption-0.1.3.dist-info/RECORD
