Metadata-Version: 2.1
Name: FernetEncryption
Version: 0.1.3
Summary: Python app for encrypting messages with fernet cryptography.
Home-page: https://github.com/MysticTechnology/FernetEncryption
Author: Mystic
Author-email: mystic.technology.mail@gmail.com
License: MIT
Keywords: cryptography,encryption,security
Platform: UNKNOWN
Classifier: Development Status :: 3 - Alpha
Classifier: License :: OSI Approved :: MIT License
Classifier: Natural Language :: English
Classifier: Operating System :: OS Independent
Classifier: Programming Language :: Python
Classifier: Programming Language :: Python :: 3
Classifier: Programming Language :: Python :: 3 :: Only
Classifier: Programming Language :: Python :: 3.8
Classifier: Programming Language :: Python :: 3.9
Classifier: Intended Audience :: Developers
Classifier: Intended Audience :: Science/Research
Classifier: Intended Audience :: Information Technology
Classifier: Intended Audience :: Financial and Insurance Industry
Classifier: Topic :: Security
Classifier: Topic :: Security :: Cryptography
Requires-Python: >=3.8
License-File: LICENSE
Requires-Dist: cryptography (==2.9.2)
